MANIFEST.in
README.md
setup.py
atomicpress/__init__.py
atomicpress/admin.py
atomicpress/app.py
atomicpress/commands.py
atomicpress/context_processors.py
atomicpress/filters.py
atomicpress/models.py
atomicpress/views.py
atomicpress.egg-info/PKG-INFO
atomicpress.egg-info/SOURCES.txt
atomicpress.egg-info/dependency_links.txt
atomicpress.egg-info/not-zip-safe
atomicpress.egg-info/requires.txt
atomicpress.egg-info/top_level.txt
atomicpress/ext/__init__.py
atomicpress/ext/exporter/__init__.py
atomicpress/ext/ftp/__init__.py
atomicpress/ext/importer/__init__.py
atomicpress/ext/prefill/__init__.py
atomicpress/ext/s3/__init__.py
atomicpress/migrations/README
atomicpress/migrations/alembic.ini
atomicpress/migrations/env.py
atomicpress/migrations/env.pyc
atomicpress/migrations/script.py.mako
atomicpress/migrations/versions/127682c11a74_.py
atomicpress/migrations/versions/127682c11a74_.pyc
atomicpress/migrations/versions/1a8ee645def6_.py
atomicpress/migrations/versions/1a8ee645def6_.pyc
atomicpress/migrations/versions/591f74b599d5_.py
atomicpress/migrations/versions/591f74b599d5_.pyc
atomicpress/templates/.DS_Store
atomicpress/templates/admin/home.html
atomicpress/themes/__init__.py
atomicpress/themes/minimal/__init__.py
atomicpress/themes/minimal/helpers.py
atomicpress/themes/minimal/views.py
atomicpress/themes/minimal/static/.jshintrc
atomicpress/themes/minimal/static/gulpfile.js
atomicpress/themes/minimal/static/package.json
atomicpress/themes/minimal/static/builds/css/main-min.css
atomicpress/themes/minimal/static/builds/css/main.css
atomicpress/themes/minimal/static/builds/img/.DS_Store
atomicpress/themes/minimal/static/builds/img/favicon.ico
atomicpress/themes/minimal/static/gulp/config.js
atomicpress/themes/minimal/static/gulp/config.template.js
atomicpress/themes/minimal/static/gulp/index.js
atomicpress/themes/minimal/static/gulp/tasks/browserify.js
atomicpress/themes/minimal/static/gulp/tasks/build.js
atomicpress/themes/minimal/static/gulp/tasks/default.js
atomicpress/themes/minimal/static/gulp/tasks/images.js
atomicpress/themes/minimal/static/gulp/tasks/less.js
atomicpress/themes/minimal/static/gulp/tasks/watch.js
