Metadata-Version: 1.1
Name: atomicpress
Version: 1.0.16
Summary: AtomicPress is a static blog generator for python developers.
Home-page: https://github.com/marteinn/atomicpress
Author: Martin Sandström
Author-email: martin@marteinn.se
License: MIT
Platform: UNKNOWN
Classifier: Development Status :: 4 - Beta
Classifier: Environment :: Web Environment
Classifier: Intended Audience :: Developers
Classifier: Natural Language :: English
Classifier: License :: OSI Approved :: MIT License
Classifier: Programming Language :: Python
Classifier: Programming Language :: Python :: 2
Classifier: Programming Language :: Python :: 2.7
